peewee_aio/__init__.py
peewee_aio/databases.py
peewee_aio/fields.py
peewee_aio/manager.py
peewee_aio/model.py
peewee_aio/py.typed
peewee_aio/types.py
peewee_aio/utils.py
peewee_aio-1.7.3.dist-info/METADATA
peewee_aio-1.7.3.dist-info/WHEEL
peewee_aio-1.7.3.dist-info/RECORD
