Metadata-Version: 2.1
Name: peewee-aio
Version: 1.7.3
Summary: Async support for Peewee ORM
Home-page: https://github.com/klen/peewee-aio
License: MIT
Keywords: peewee,asyncio,trio,orm
Author: Kirill Klenov
Author-email: horneds@gmail.com
Requires-Python: >=3.8,<4.0
Classifier: Development Status :: 5 - Production/Stable
Classifier: Framework :: AsyncIO
Classifier: Framework :: Trio
Classifier: Intended Audience :: Developers
Classifier: License :: OSI Approved :: MIT License
Classifier: Programming Language :: Python
Classifier: Programming Language :: Python :: 3
Classifier: Programming Language :: Python :: 3.8
Classifier: Programming Language :: Python :: 3.9
Classifier: Programming Language :: Python :: 3.10
Classifier: Programming Language :: Python :: 3.11
Provides-Extra: aiomysql
Provides-Extra: aiopg
Provides-Extra: aiosqlite
Provides-Extra: asyncpg
Provides-Extra: trio-mysql
Provides-Extra: triopg
Requires-Dist: aio-databases (>=0,<1)
Requires-Dist: aiomysql ; extra == "aiomysql"
Requires-Dist: aiopg ; extra == "aiopg"
Requires-Dist: aiosqlite ; extra == "aiosqlite"
Requires-Dist: asyncpg ; extra == "asyncpg"
Requires-Dist: peewee (>=3,<4)
Requires-Dist: trio_mysql ; extra == "trio-mysql"
Requires-Dist: triopg ; extra == "triopg"
Requires-Dist: typing-extensions ; python_version < "3.11"
Project-URL: Repository, https://github.com/klen/peewee-aio
